goldeneye/__init__.py
goldeneye/datasets/__init__.py
goldeneye/datasets/de_dataset.py
goldeneye/datasets/xlrs_bench.py
goldeneye/hud.py
goldeneye/models/__init__.py
goldeneye/models/base.py
goldeneye/models/describe_earth.py
goldeneye/models/earthdial.py
goldeneye/models/geochat/__init__.py
goldeneye/models/geochat/geochat.py
goldeneye/models/geochat/modeling_geochat.py
goldeneye/models/geollava/__init__.py
goldeneye/models/geollava/_longva_inference.py
goldeneye/models/geollava/geollava.py
goldeneye/models/geor1.py
goldeneye/models/geozero.py
goldeneye/models/registry.py
goldeneye/models/utils.py
goldeneye/models/zoomearth.py
goldeneye/report.py
goldeneye-0.1.0.dist-info/WHEEL
goldeneye-0.1.0.dist-info/METADATA
goldeneye-0.1.0.dist-info/RECORD
