Metadata-Version: 2.4
Name: goldeneye
Version: 0.1.0
Summary: Simple unified interface for geospatial vision-language models.
Keywords: deep-learning,geospatial,machine-learning,remote-sensing,vision-language-models,vlm
Author: Isaac Corley
Author-email: Isaac Corley <isaac.corley@proton.me>
License-Expression: MIT
Classifier: Development Status :: 4 - Beta
Classifier: Intended Audience :: Developers
Classifier: Intended Audience :: Science/Research
Classifier: License :: OSI Approved :: MIT License
Classifier: Operating System :: OS Independent
Classifier: Programming Language :: Python :: 3 :: Only
Classifier: Programming Language :: Python :: 3.13
Classifier: Programming Language :: Python :: 3.14
Classifier: Topic :: Scientific/Engineering :: Artificial Intelligence
Classifier: Topic :: Scientific/Engineering :: GIS
Classifier: Topic :: Scientific/Engineering :: Image Processing
Requires-Dist: accelerate>=1
Requires-Dist: bitsandbytes>=0.49.1
Requires-Dist: datasets>=2.14
Requires-Dist: einops>=0.8
Requires-Dist: hf-transfer>=0.1
Requires-Dist: pillow>=10
Requires-Dist: protobuf>=6.33.2
Requires-Dist: pycocotools>=2.0.11
Requires-Dist: qwen-vl-utils>=0.0.8
Requires-Dist: sam2>=1.1
Requires-Dist: sentencepiece>=0.2
Requires-Dist: supervision>=0.22
Requires-Dist: timm>=0.9.16
Requires-Dist: torch>=2.9
Requires-Dist: torchvision>=0.20
Requires-Dist: transformers>=4.40
Requires-Python: >=3.13
Project-URL: Homepage, https://github.com/isaaccorley/goldeneye
Project-URL: Issues, https://github.com/isaaccorley/goldeneye/issues
Project-URL: Repository, https://github.com/isaaccorley/goldeneye
